pydho800/__init__.py
pydho800/pydho800.py
pydho800-0.0.10.dist-info/LICENSE.md
pydho800-0.0.10.dist-info/METADATA
pydho800-0.0.10.dist-info/WHEEL
pydho800-0.0.10.dist-info/top_level.txt
pydho800-0.0.10.dist-info/RECORD
