Metadata-Version: 2.1
Name: pydho800
Version: 0.0.10
Summary: Rigol 800 control library (unofficial)
Home-page: https://github.com/MasterJubei/pydho800
Author: Jubei
Author-email: jubei@puffkrush.org
Classifier: Programming Language :: Python :: 3
Classifier: License :: OSI Approved :: BSD License
Classifier: Operating System :: OS Independent
Requires-Python: >=3.6
License-File: LICENSE.md
Requires-Dist: pylabdevs-tspspi >=0.0.11
